taskforce
