Metadata-Version: 1.1
Name: taskforce
Version: 0.3.5
Summary: Taskforce starts and restarts daemon processes.
Home-page: https://github.com/akfullfo/taskforce
Author: Andrew Fullford
Author-email: pypi102014@fullford.com
License: Apache License, Version 2.0
Download-URL: https://github.com/akfullfo/taskforce/tarball/0.3.5
Platform: Linux
Platform: BSD
Platform: Mac OS X
Classifier: Development Status :: 4 - Beta
Classifier: Environment :: No Input/Output (Daemon)
Classifier: Intended Audience :: Developers
Classifier: Intended Audience :: System Administrators
Classifier: License :: OSI Approved :: Apache Software License
Classifier: Operating System :: POSIX :: Linux
Classifier: Operating System :: POSIX :: BSD
Classifier: Operating System :: MacOS :: MacOS X
Classifier: Programming Language :: Python :: 2.7
Classifier: Programming Language :: Python :: 3.3
Classifier: Programming Language :: Python :: 3.4
Classifier: Topic :: System :: Distributed Computing
Classifier: Topic :: System :: Software Distribution
Classifier: Topic :: System :: Systems Administration
Classifier: Topic :: Utilities
Requires: PyYAML
Provides: taskforce
